trajectory_analysis_tools/__init__.py
trajectory_analysis_tools/distance1D.py
trajectory_analysis_tools/distance2D.py
trajectory_analysis_tools/highest_posterior_density.py
trajectory_analysis_tools/posterior.py
trajectory_analysis_tools-1.1.0.dist-info/METADATA
trajectory_analysis_tools-1.1.0.dist-info/WHEEL
trajectory_analysis_tools-1.1.0.dist-info/top_level.txt
trajectory_analysis_tools-1.1.0.dist-info/RECORD
